{
  "appPort": ["9123:8123"],
  "context": "..",
  "extensions": [
    "ms-python.python",
    "github.vscode-pull-request-github",
    "ryanluker.vscode-coverage-gutters",
    "ms-python.vscode-pylance"
  ],
  "image": "ghcr.io/ludeeus/devcontainer/integration:stable",
  "name": "Bodymiscale Development",
  "postCreateCommand": "container install && pip install --ignore-installed -r requirements.txt",
  "settings": {
    "editor.formatOnPaste": false,
    "editor.formatOnSave": true,
    "editor.formatOnType": true,
    "editor.tabSize": 4,
    "files.eol": "\n",
    "files.trimTrailingWhitespace": true,
    "python.analysis.autoSearchPaths": false,
    "python.formatting.provider": "black",
    "python.linting.enabled": true,
    "python.linting.pylintArgs": ["--disable", "import-error"],
    "python.linting.pylintEnabled": true,
    "python.pythonPath": "/usr/local/python/bin/python",
    "terminal.integrated.defaultProfile.linux": "zsh",
    "terminal.integrated.profiles.linux": {
      "zsh": {
        "path": "/usr/bin/zsh"
      }
    }
  }
}
